{
  "name": "Direction",
  "base": "PersistedModel",
  "idInjection": true,
  "options": {
    "validateUpsert": true
  },
  "properties": {
    "libelle": {
      "type": "string",
      "required": true
    },
    "description": {
      "type": "string",
      "required": true
    }
  },
  "validations": [],
  "relations": {
    "Vehicule": {
      "type": "hasMany",
      "model": "Vehicule",
      "foreignKey": ""
    },
    "utilisateurs": {
      "type": "hasMany",
      "model": "Utilisateur",
      "foreignKey": ""
    }
  },
  "acls": [],
  "methods": {}
}
